myownsample.py
myownsample-0.0.1.dist-info/LICENSE
myownsample-0.0.1.dist-info/METADATA
myownsample-0.0.1.dist-info/WHEEL
myownsample-0.0.1.dist-info/top_level.txt
myownsample-0.0.1.dist-info/RECORD
